{
"devices": [
	{
		"id" : 2769,
		"device_id" : 3,
		"quantity" : "1",
		"calc_quantity" : "1",
		"weight" : "85773.94",
		"zero_weight" : "103194.99",
		"unit_weight" : "8612.660000000003",
		"calc_weight" : "111809.96",
		"quantity_min_threshold" : "0",
		"quantity_crit_threshold" : "0",
		"mac_address" : null,
		"chip_id" : null,
		"heartbeat" : "1753880827112",
		"setup_timestamp" : null,
		"zero_timestamp" : null,
		"weight_history" : "[111810.29,111810.62,111810.84,111810.78,111810.15,111810.15,111807.78,111815.16,111807.92,111809.97,111799.06]",
		"count" : 0,
		"status" : "running",
		"created_at" : "2024-11-21 07:00:59",
		"updated_at" : "2025-07-30 13:07:07",
		"changeqty" : 0,
		"bin_id" : 1,
		"item_id" : 29,
		"is_sync" : 1,
		"retry_count" : 0,
		"is_update_weight" : 1,
		"damage_quantity" : 0,
		"description": 	{
			"name" : "JFS_1_1_PPE Box_STAS\/JFS\/21",
			"part_number" : "STAS\/JFS\/21",
			"material_no" : "",
			"supplier_email" : "",
			"matl_grp" : "",
			"cri_code" : "",
			"jom" : "",
			"item_acct" : "",
			"field1" : "",
			"expiry_bag" : "NA",
			"expiry_bag2" : "NA",
			"expiry_bag3" : "NA",
			"quantity_bag" : "",
			"quantity_bag2" : "",
			"quantity_bag3" : "",
			"bag_no_batch" : null,
			"bag_no_batch2" : null,
			"bag_no_batch3" : null,
			"created_at" : "2024-11-21 07:08:43",
			"updated_at" : "2024-11-21 07:08:43"
		}
	},
	{
		"id" : 2782,
		"device_id" : 4,
		"quantity" : "1",
		"calc_quantity" : "1",
		"weight" : "84920.59",
		"zero_weight" : "102557.59",
		"unit_weight" : "8826.259999999995",
		"calc_weight" : "111374.56",
		"quantity_min_threshold" : "0",
		"quantity_crit_threshold" : "0",
		"mac_address" : null,
		"chip_id" : null,
		"heartbeat" : "1753880827418",
		"setup_timestamp" : null,
		"zero_timestamp" : null,
		"weight_history" : "[111377.81,111377.85,111377.8,111377.74,111377.78,111377.82,111377.9,111377.38,111377.29,111376.91,111373.92]",
		"count" : 0,
		"status" : "running",
		"created_at" : "2024-11-21 07:09:00",
		"updated_at" : "2025-07-30 13:07:07",
		"changeqty" : 0,
		"bin_id" : 2,
		"item_id" : 13,
		"is_sync" : 1,
		"retry_count" : 0,
		"is_update_weight" : 1,
		"damage_quantity" : 0,
		"description": 	{
			"name" : "JFS_1_2_Torch Light_CAB\/JFC1\/08",
			"part_number" : "CAB\/JFC1\/08",
			"material_no" : "",
			"supplier_email" : "",
			"matl_grp" : "",
			"cri_code" : "",
			"jom" : "",
			"item_acct" : "",
			"field1" : "",
			"expiry_bag" : "NA",
			"expiry_bag2" : "NA",
			"expiry_bag3" : "NA",
			"quantity_bag" : "",
			"quantity_bag2" : "",
			"quantity_bag3" : "",
			"bag_no_batch" : null,
			"bag_no_batch2" : null,
			"bag_no_batch3" : null,
			"created_at" : "2024-11-21 07:11:26",
			"updated_at" : "2024-11-21 07:11:26"
		}
	},
	{
		"id" : 2994,
		"device_id" : 5,
		"quantity" : null,
		"calc_quantity" : null,
		"weight" : "83962.28",
		"zero_weight" : "83962.28",
		"unit_weight" : null,
		"calc_weight" : null,
		"quantity_min_threshold" : null,
		"quantity_crit_threshold" : null,
		"mac_address" : null,
		"chip_id" : null,
		"heartbeat" : "1753880700271",
		"setup_timestamp" : null,
		"zero_timestamp" : null,
		"weight_history" : null,
		"count" : 0,
		"status" : "running",
		"created_at" : "2025-07-30 13:04:58",
		"updated_at" : "2025-07-30 13:05:00",
		"changeqty" : 0,
		"bin_id" : null,
		"item_id" : null,
		"is_sync" : 0,
		"retry_count" : 0,
		"is_update_weight" : 1,
		"damage_quantity" : 0,
		"description": {
			"name" : "JFS_1_4_Digital Mutimeter_1120184219",
			"part_number" : "1120184219",
			"material_no" : "",
			"supplier_email" : "",
			"matl_grp" : "",
			"cri_code" : "",
			"jom" : "",
			"item_acct" : "",
			"field1" : "",
			"expiry_bag" : "NA",
			"expiry_bag2" : "NA",
			"expiry_bag3" : "NA",
			"quantity_bag" : "",
			"quantity_bag2" : "",
			"quantity_bag3" : "",
			"bag_no_batch" : null,
			"bag_no_batch2" : null,
			"bag_no_batch3" : null,
			"created_at" : "2024-11-21 07:15:32",
			"updated_at" : "2024-11-21 07:15:32"
		}
	}
]}
